qset_feature_store/__init__.py
qset_feature_store/archive/__init__.py
qset_feature_store/archive/dataset_manager/__init__.py
qset_feature_store/archive/dataset_manager/streaming_dataset_manager.py
qset_feature_store/archive/streaming_server.py
qset_feature_store/archive/streaming_server.yml
qset_feature_store/archive/worker/__init__.py
qset_feature_store/archive/worker/dataset/__init__.py
qset_feature_store/archive/worker/dataset/build.bat
qset_feature_store/archive/worker/dataset/dataset_worker.py
qset_feature_store/archive/worker/dataset/deployment.yml
qset_feature_store/archive/worker/dataset/Dockerfile
qset_feature_store/archive/worker/dataset/main.py
qset_feature_store/archive/worker/dataset/push.bat
qset_feature_store/archive/worker/dataset/run.bat
qset_feature_store/archive/worker/historical.py
qset_feature_store/controller/__init__.py
qset_feature_store/controller/controller.py
qset_feature_store/featureset_engine/__init__.py
qset_feature_store/featureset_engine/dataset_manager/__init__.py
qset_feature_store/featureset_engine/dataset_manager/data/local/6026716f1ae81052b43a9818/6026716f1ae81052b43a9818.parquet
qset_feature_store/featureset_engine/dataset_manager/data/local/6026721a87f650a55707dfdb/6026721a87f650a55707dfdb.parquet
qset_feature_store/featureset_engine/dataset_manager/data/local/60267e93e653a081d4e5456e/60267e93e653a081d4e5456e.parquet
qset_feature_store/featureset_engine/dataset_manager/data/local/602a170a9d5e0dd1173f7956/602a170a9d5e0dd1173f7956.parquet
qset_feature_store/featureset_engine/dataset_manager/data/local/602a17284e0f5bc2e64031d2/602a17284e0f5bc2e64031d2.parquet
qset_feature_store/featureset_engine/dataset_manager/data/local/602a1749ec11cc0d869773dd/602a1749ec11cc0d869773dd.parquet
qset_feature_store/featureset_engine/dataset_manager/data/local/602a18b5d359dc90e893dddf/602a18b5d359dc90e893dddf.parquet
qset_feature_store/featureset_engine/dataset_manager/data/local/602a19077cd15c8858ac48dd/602a19077cd15c8858ac48dd.parquet
test_qset_feature_store-0.1.3.dist-info/WHEEL
test_qset_feature_store-0.1.3.dist-info/METADATA
test_qset_feature_store-0.1.3.dist-info/RECORD
