Metadata-Version: 2.1
Name: test-qset-feature-store
Version: 0.1.3
Summary: 
Author: Arsenii Kadaner
Author-email: arseniikadaner@gmail.com
Requires-Python: >=3.7.1,<4.0.0
Classifier: Programming Language :: Python :: 3
Classifier: Programming Language :: Python :: 3.8
Classifier: Programming Language :: Python :: 3.9
Requires-Dist: utils-ak (>=0.1.6,<0.2.0)
